sm_chat/__init__.py
sm_chat-1767581.686.835.dist-info/licenses/LICENSE
sm_chat-1767581.686.835.dist-info/METADATA
sm_chat-1767581.686.835.dist-info/WHEEL
sm_chat-1767581.686.835.dist-info/top_level.txt
sm_chat-1767581.686.835.dist-info/RECORD
