Metadata-Version: 2.4
Name: sm-chat
Version: 1767581.686.835
Summary: High-quality integration for https://supermaker.ai/chat/
Home-page: https://supermaker.ai/chat/
Author: SuperMaker
Classifier: Programming Language :: Python :: 3
Classifier: License :: OSI Approved :: MIT License
Requires-Python: >=3.6
License-File: LICENSE
Dynamic: author
Dynamic: classifier
Dynamic: description
Dynamic: description-content-type
Dynamic: home-page
Dynamic: license-file
Dynamic: requires-python
Dynamic: summary
